{
  "name": "Daging Belengas Khairul Aming (Ringkas & Mudah)",
  "chef": "Khairul Aming",
  "source": "resipikita.com/resepi-daging-belengas-khairul-aming",
  "image_url": "",
  "raw_text": "Recipe: Daging Belengas Khairul Aming (Ringkas & Mudah)\nChef: Khairul Aming\n\nINGREDIENTS:\n- Daging lembu (1.5kg - 2kg)\n- Lemak daging (jika ada)\n- 1 sudu kecil serbuk kunyit\n- Minyak masak\n- 7 ulas bawang putih\n- 1 ketul halia\n- Kicap karamel (atau kicap manis)\n- Sos cili\n- Sos tomato\n- Sos tiram\n- Garam secukup rasa\n- Bawang Holland (hiris)\n- Cili padi (hiris)\n- Kacang panjang (potong)\n\nINSTRUCTIONS:\n1. Keluarkan daging dari peti sejuk. Kalau ada lemak daging, tambah sikit untuk rasa yang lebih sedap.\n2. Rebus daging dalam air selama 30 minit atau sampai daging empuk dan air hampir kering.\n3. Lepas tu, masukkan serbuk kunyit dan sedikit minyak masak supaya daging jadi garing.\n4. Blend bawang putih dan halia sampai halus, lepas tu masukkan dalam periuk.\n5. Campak kicap karamel (atau kicap manis), sos cili, sos tomato, dan sos tiram. Tak perlu risau sangat pasal ukuran, campak je!\n6. Perasakan dengan garam dan serbuk rasa secukupnya. Kalau nampak kering, tambah sikit air.\n7. Masukkan bawang Holland, cili padi, dan kacang panjang. Kacau semua bahan sampai sebati.\n8. Siap! Hidangkan dengan nasi putih yang simple. Selamat mencuba!\n",
  "scraped_at": "2026-04-09T01:58:06.514746+00:00"
}