{
  "name": "Kuih Lopes (Sedap & Confirm Jadi)",
  "chef": "Khairul Aming",
  "source": "resipikita.com/resepi-kuih-lopes-sedap",
  "image_url": "",
  "raw_text": "Recipe: Kuih Lopes (Sedap & Confirm Jadi)\nChef: Khairul Aming\n\nINGREDIENTS:\n- Setengah cawan kapur udara\n- 1 setengah cawan air\n- 500g beras pulut (yang sudah dibasuh bersih)\n- Kelapa parut putih (yang dah dicampur sedikit garam sebagai perasa)\n- 5- 6 helai daun pisang\n- 8 helai daun pandan fresh\n\nINSTRUCTIONS:\n1. Start dengan memotong daun pandan tu kecil-kecil, lepastu blend dengan air. Dah blend, tapis untuk buang serat-serat kasar tu dan kita akan dapat jus pandan yang pekat.\n2. Ambil semua bahan yang kita dah sediakan kecuali kelapa parut tu ya, gaulkan dalam satu bekas. Pastikan kacau dengan gaya chef pro selama lebih kurang 10 minit dengan api yang ala-ala medium. Kita taknak ada kerak terbentuk kat dasar periuk.\n3. Lepas tu, masak sampai pulut tu ‘al dente’, maknanya masih ada sikit keras di tengah. Cam pasta Itali tu haa.\n4. Ok, skang kita bersihkan daun pisang dan potong ke size lebih kurang 10 inci dengan 6 inci. Nak buat dia jadi lebih lembut dan senang bentuk, layurkan sikit atas api.\n5. Ambik sebahagian dari beras pulut yang dah masak, agak-agak satu cawan macam tu, dan bungkus ngan daun pisang. Roll kemas-kemas bentuk macam silinder. Pastikan ikat kuat dengan tali kat hujung-hujungnya.\n6. Siapkan periuk dengan alas daun pisang kat dasar, dan susun bungkus-bungkus pulut yang dah siap tu. Isikan air sampai semua bungkusan tu tenggelam. Panaskan sampai air tu fully wap.\n7. Dah siap, biarkan sejuk sikit sebelum potong guna benang yang kuat. Pastikan potongan bersih.\n8. Last step, guling-gulingkan dalam kelapa parut. Biar setiap keping tu merasa kasih sayang kelapa tu.\n9. Sedia untuk dinikmati! Jangan lupa siram sikit air gula melaka atasnya untuk extra kick!\n",
  "scraped_at": "2026-04-09T01:58:06.523969+00:00"
}